{
	"hero": {
		"image": [
			{
				"url": "//d1fl2om3sc0eid.cloudfront.net/img/p/5016/f.jpg",
				"text": ""
			}
		],
		"title": "Viajes <span>inolvidables</span> a precios <span>increíbles</span>"
	},
	"slides": [
		{
			"name": "Americas",
			"description": "Sumérgete en sus vibrantes culturas y paisajes naturales desde el polo hasta el trópico. Maravíllate con la arquitectura colonial y las ruinas antiguas llenas de misterio y sorpresas.\n                            ",
			"totalCampaigns": 12,
			"slug": "/mx/america",
			"type": "continent",
			"title": "Disfruta <span>América</span>",
			"icon": "america-stamp",
			"background": "1_bg",
			"cards": [
				{
					"id": 11574,
					"title": "Capitales, Iguazú y Los Glaciares",
					"destination": "Argentina y Brasil",
					"images": [
						{
							"desktop": "https://d1fl2om3sc0eid.cloudfront.net/img/p/11574/c251531.jpg",
							"tablet": "https://d1fl2om3sc0eid.cloudfront.net/img/p/11574/c251531.jpg",
							"mobile": "https://d1fl2om3sc0eid.cloudfront.net/img/p/11574/c251531.jpg"
						}
					],
					"days": 15,
					"url": "/mx/circuitos/america/11574-capitales-iguazu-y-los-glaciares",
					"map": null,
					"highlights": null,
					"includes": null,
					"priceDetail": {
						"fromPrice": 35599,
						"fromPriceBeautify": "$35,599",
						"discountSaved": 0,
						"oldPriceBeautify": "$99",
						"pricingPercentage": 0,
						"pricePerNight": "$2,543"
					},
					"tags": null,
					"crafterDetail": null,
					"hasPrivateTour": true,
					"hasSoloTraveller": true,
					"headLine": null,
					"tagHeadLine": [],
					"isLandOnly": false,
					"isValid": true,
					"extraNights": 11
				},
				{
					"id": 11573,
					"title": "Pura Vida y Paraíso en Tamarindo",
					"destination": "Costa Rica",
					"images": [
						{
							"desktop": "https://d1fl2om3sc0eid.cloudfront.net/img/p/11573/c251511.jpg",
							"tablet": "https://d1fl2om3sc0eid.cloudfront.net/img/p/11573/c251511.jpg",
							"mobile": "https://d1fl2om3sc0eid.cloudfront.net/img/p/11573/c251511.jpg"
						}
					],
					"days": 10,
					"url": "/mx/naturaleza/america/11573-pura-vida-y-paraiso-en-tamarindo",
					"map": null,
					"highlights": null,
					"includes": null,
					"priceDetail": {
						"fromPrice": 25199,
						"fromPriceBeautify": "$25,199",
						"discountSaved": 11090,
						"oldPriceBeautify": "$36,299",
						"pricingPercentage": 30,
						"pricePerNight": "$2,800"
					},
					"tags": null,
					"crafterDetail": null,
					"hasPrivateTour": false,
					"hasSoloTraveller": true,
					"headLine": null,
					"tagHeadLine": [],
					"isLandOnly": false,
					"isValid": true,
					"extraNights": 0
				},
				{
					"id": 11572,
					"title": "La Tierra Sagrada de los Incas",
					"destination": "Perú",
					"images": [
						{
							"desktop": "https://d1fl2om3sc0eid.cloudfront.net/img/p/11572/c279641.jpg",
							"tablet": "https://d1fl2om3sc0eid.cloudfront.net/img/p/11572/c279641.jpg",
							"mobile": "https://d1fl2om3sc0eid.cloudfront.net/img/p/11572/c279641.jpg"
						}
					],
					"days": 9,
					"url": "/mx/circuitos/america/11572-la-tierra-sagrada-de-los-incas",
					"map": null,
					"highlights": null,
					"includes": null,
					"priceDetail": {
						"fromPrice": 28099,
						"fromPriceBeautify": "$28,099",
						"discountSaved": 26420,
						"oldPriceBeautify": "$54,599",
						"pricingPercentage": 48,
						"pricePerNight": "$3,512"
					},
					"tags": null,
					"crafterDetail": null,
					"hasPrivateTour": false,
					"hasSoloTraveller": true,
					"headLine": null,
					"tagHeadLine": [],
					"isLandOnly": false,
					"isValid": true,
					"extraNights": 0
				},
				{
					"id": 11576,
					"title": "Aventura en Amazonas y Galápagos",
					"destination": "Ecuador",
					"images": [
						{
							"desktop": "https://d1fl2om3sc0eid.cloudfront.net/img/p/11576/c251557.jpg",
							"tablet": "https://d1fl2om3sc0eid.cloudfront.net/img/p/11576/c251557.jpg",
							"mobile": "https://d1fl2om3sc0eid.cloudfront.net/img/p/11576/c251557.jpg"
						}
					],
					"days": 12,
					"url": "/mx/circuitos/america/11576-aventura-en-amazonas-y-galapagos",
					"map": null,
					"highlights": null,
					"includes": null,
					"priceDetail": {
						"fromPrice": 33099,
						"fromPriceBeautify": "$33,099",
						"discountSaved": 32110,
						"oldPriceBeautify": "$65,299",
						"pricingPercentage": 49,
						"pricePerNight": "$3,009"
					},
					"tags": null,
					"crafterDetail": null,
					"hasPrivateTour": false,
					"hasSoloTraveller": true,
					"headLine": null,
					"tagHeadLine": [],
					"isLandOnly": false,
					"isValid": true,
					"extraNights": 0
				},
				{
					"id": 12059,
					"title": "La Última Aventura Inca",
					"destination": "Perú",
					"images": [
						{
							"desktop": "https://d1fl2om3sc0eid.cloudfront.net/img/p/12059/c283022.jpg",
							"tablet": "https://d1fl2om3sc0eid.cloudfront.net/img/p/12059/c283022.jpg",
							"mobile": "https://d1fl2om3sc0eid.cloudfront.net/img/p/12059/c283022.jpg"
						}
					],
					"days": 15,
					"url": "/mx/circuitos/america/12059-la-ultima-aventura-inca",
					"map": null,
					"highlights": null,
					"includes": null,
					"priceDetail": {
						"fromPrice": 37499,
						"fromPriceBeautify": "$37,499",
						"discountSaved": 26630,
						"oldPriceBeautify": "$64,199",
						"pricingPercentage": 41,
						"pricePerNight": "$2,679"
					},
					"tags": null,
					"crafterDetail": null,
					"hasPrivateTour": false,
					"hasSoloTraveller": true,
					"headLine": null,
					"tagHeadLine": [],
					"isLandOnly": false,
					"isValid": true,
					"extraNights": 0
				},
				{
					"id": 12052,
					"title": "La noche mágica de las tortugas marinas",
					"destination": "Costa Rica",
					"images": [
						{
							"desktop": "https://d1fl2om3sc0eid.cloudfront.net/img/p/12052/c283036.jpg",
							"tablet": "https://d1fl2om3sc0eid.cloudfront.net/img/p/12052/c283036.jpg",
							"mobile": "https://d1fl2om3sc0eid.cloudfront.net/img/p/12052/c283036.jpg"
						}
					],
					"days": 15,
					"url": "/mx/circuitos/america/12052-la-noche-magica-de-las-tortugas-marinas",
					"map": null,
					"highlights": null,
					"includes": null,
					"priceDetail": {
						"fromPrice": 25499,
						"fromPriceBeautify": "$25,499",
						"discountSaved": 15560,
						"oldPriceBeautify": "$41,099",
						"pricingPercentage": 37,
						"pricePerNight": "$1,821"
					},
					"tags": null,
					"crafterDetail": null,
					"hasPrivateTour": false,
					"hasSoloTraveller": true,
					"headLine": null,
					"tagHeadLine": [],
					"isLandOnly": false,
					"isValid": true,
					"extraNights": 0
				},
				{
					"id": 12047,
					"title": "El Gigante del Sur",
					"destination": "Brasil",
					"images": [
						{
							"desktop": "https://d1fl2om3sc0eid.cloudfront.net/img/p/12047/c279653.jpg",
							"tablet": "https://d1fl2om3sc0eid.cloudfront.net/img/p/12047/c279653.jpg",
							"mobile": "https://d1fl2om3sc0eid.cloudfront.net/img/p/12047/c279653.jpg"
						}
					],
					"days": 15,
					"url": "/mx/circuitos/america/12047-el-gigante-del-sur",
					"map": null,
					"highlights": null,
					"includes": null,
					"priceDetail": {
						"fromPrice": 33399,
						"fromPriceBeautify": "$33,399",
						"discountSaved": 33400,
						"oldPriceBeautify": "$66,799",
						"pricingPercentage": 50,
						"pricePerNight": "$2,386"
					},
					"tags": null,
					"crafterDetail": null,
					"hasPrivateTour": false,
					"hasSoloTraveller": true,
					"headLine": null,
					"tagHeadLine": [],
					"isLandOnly": false,
					"isValid": true,
					"extraNights": 10
				},
				{
					"id": 12046,
					"title": "Capitales latinas y viñedos de Mendoza",
					"destination": "Chile, Argentina y Brasil",
					"images": [
						{
							"desktop": "https://d1fl2om3sc0eid.cloudfront.net/img/p/12046/c259759.jpg",
							"tablet": "https://d1fl2om3sc0eid.cloudfront.net/img/p/12046/c259759.jpg",
							"mobile": "https://d1fl2om3sc0eid.cloudfront.net/img/p/12046/c259759.jpg"
						}
					],
					"days": 18,
					"url": "/mx/circuitos/america/12046-capitales-latinas-y-vinedos-de-mendoza",
					"map": null,
					"highlights": null,
					"includes": null,
					"priceDetail": {
						"fromPrice": 46099,
						"fromPriceBeautify": "$46,099",
						"discountSaved": 25360,
						"oldPriceBeautify": "$71,499",
						"pricingPercentage": 35,
						"pricePerNight": "$2,712"
					},
					"tags": null,
					"crafterDetail": null,
					"hasPrivateTour": true,
					"hasSoloTraveller": true,
					"headLine": null,
					"tagHeadLine": [],
					"isLandOnly": false,
					"isValid": true,
					"extraNights": 0
				},
				{
					"id": 12020,
					"title": "De Buenos Aires al fin del mundo",
					"destination": "Argentina ",
					"images": [
						{
							"desktop": "https://d1fl2om3sc0eid.cloudfront.net/img/p/12020/c259280.jpg",
							"tablet": "https://d1fl2om3sc0eid.cloudfront.net/img/p/12020/c259280.jpg",
							"mobile": "https://d1fl2om3sc0eid.cloudfront.net/img/p/12020/c259280.jpg"
						}
					],
					"days": 19,
					"url": "/mx/circuitos/america/12020-de-buenos-aires-al-fin-del-mundo",
					"map": null,
					"highlights": null,
					"includes": null,
					"priceDetail": {
						"fromPrice": 57699,
						"fromPriceBeautify": "$57,699",
						"discountSaved": 51930,
						"oldPriceBeautify": "$109,699",
						"pricingPercentage": 47,
						"pricePerNight": "$3,206"
					},
					"tags": null,
					"crafterDetail": null,
					"hasPrivateTour": false,
					"hasSoloTraveller": true,
					"headLine": null,
					"tagHeadLine": [],
					"isLandOnly": false,
					"isValid": true,
					"extraNights": 0
				},
				{
					"id": 12057,
					"title": "Inca Sagrado y Última Aventura Amazónica",
					"destination": "Perú",
					"images": [
						{
							"desktop": "https://d1fl2om3sc0eid.cloudfront.net/img/p/12057/c283032.jpg",
							"tablet": "https://d1fl2om3sc0eid.cloudfront.net/img/p/12057/c283032.jpg",
							"mobile": "https://d1fl2om3sc0eid.cloudfront.net/img/p/12057/c283032.jpg"
						}
					],
					"days": 13,
					"url": "/mx/naturaleza/america/12057-inca-sagrado-y-ultima-aventura-amazonica",
					"map": null,
					"highlights": null,
					"includes": null,
					"priceDetail": {
						"fromPrice": 37099,
						"fromPriceBeautify": "$37,099",
						"discountSaved": 0,
						"oldPriceBeautify": "$99",
						"pricingPercentage": 0,
						"pricePerNight": "$3,092"
					},
					"tags": null,
					"crafterDetail": null,
					"hasPrivateTour": false,
					"hasSoloTraveller": true,
					"headLine": null,
					"tagHeadLine": [],
					"isLandOnly": false,
					"isValid": true,
					"extraNights": 0
				}
			]
		},
		{
			"name": "Asia",
			"description": "Descubre las infinitas opciones que ofrece su cultura, geografía, historia y espiritualidad. Conoce desde templos y santuarios tranquilos hasta rascacielos y calles llenas de vida. Un mundo de posibilidades.\n                            ",
			"totalCampaigns": 17,
			"slug": "/mx/asia",
			"type": "continent",
			"title": "Vive <span>Asia</span>",
			"icon": "asia-stamp",
			"background": "2_bg",
			"cards": [
				{
					"id": 11578,
					"title": "Encanto Nipón",
					"destination": "Japón",
					"images": [
						{
							"desktop": "https://d1fl2om3sc0eid.cloudfront.net/img/p/11578/c251583.jpg",
							"tablet": "https://d1fl2om3sc0eid.cloudfront.net/img/p/11578/c251583.jpg",
							"mobile": "https://d1fl2om3sc0eid.cloudfront.net/img/p/11578/c251583.jpg"
						}
					],
					"days": 13,
					"url": "/mx/ciudades/asia/11578-encanto-nipon",
					"map": null,
					"highlights": null,
					"includes": null,
					"priceDetail": {
						"fromPrice": 56299,
						"fromPriceBeautify": "$56,299",
						"discountSaved": 28150,
						"oldPriceBeautify": "$84,499",
						"pricingPercentage": 33,
						"pricePerNight": "$4,692"
					},
					"tags": null,
					"crafterDetail": null,
					"hasPrivateTour": false,
					"hasSoloTraveller": true,
					"headLine": null,
					"tagHeadLine": [],
					"isLandOnly": false,
					"isValid": true,
					"extraNights": 0
				},
				{
					"id": 11577,
					"title": "Maravillas del Reino Hachemita",
					"destination": "Jordania",
					"images": [
						{
							"desktop": "https://d1fl2om3sc0eid.cloudfront.net/img/p/11577/c251571.jpg",
							"tablet": "https://d1fl2om3sc0eid.cloudfront.net/img/p/11577/c251571.jpg",
							"mobile": "https://d1fl2om3sc0eid.cloudfront.net/img/p/11577/c251571.jpg"
						}
					],
					"days": 9,
					"url": "/mx/circuitos/asia/11577-maravillas-del-reino-hachemita",
					"map": null,
					"highlights": null,
					"includes": null,
					"priceDetail": {
						"fromPrice": 51699,
						"fromPriceBeautify": "$51,699",
						"discountSaved": 24300,
						"oldPriceBeautify": "$75,999",
						"pricingPercentage": 31,
						"pricePerNight": "$6,462"
					},
					"tags": null,
					"crafterDetail": null,
					"hasPrivateTour": false,
					"hasSoloTraveller": true,
					"headLine": null,
					"tagHeadLine": [],
					"isLandOnly": false,
					"isValid": true,
					"extraNights": 0
				},
				{
					"id": 11967,
					"title": "Bangkok, Angkor y Bahía de Halong",
					"destination": "Tailandia, Camboya y Vietnam",
					"images": [
						{
							"desktop": "https://d1fl2om3sc0eid.cloudfront.net/img/p/11967/c258383.jpg",
							"tablet": "https://d1fl2om3sc0eid.cloudfront.net/img/p/11967/c258383.jpg",
							"mobile": "https://d1fl2om3sc0eid.cloudfront.net/img/p/11967/c258383.jpg"
						}
					],
					"days": 19,
					"url": "/mx/circuitos/asia/11967-bangkok-angkor-y-bahia-de-halong",
					"map": null,
					"highlights": null,
					"includes": null,
					"priceDetail": {
						"fromPrice": 61999,
						"fromPriceBeautify": "$61,999",
						"discountSaved": 39060,
						"oldPriceBeautify": "$101,099",
						"pricingPercentage": 38,
						"pricePerNight": "$3,444"
					},
					"tags": null,
					"crafterDetail": null,
					"hasPrivateTour": false,
					"hasSoloTraveller": true,
					"headLine": null,
					"tagHeadLine": [],
					"isLandOnly": false,
					"isValid": true,
					"extraNights": 0
				},
				{
					"id": 11968,
					"title": "Palacios y desiertos de Rajastán",
					"destination": "India ",
					"images": [
						{
							"desktop": "https://d1fl2om3sc0eid.cloudfront.net/img/p/11968/c279642.jpg",
							"tablet": "https://d1fl2om3sc0eid.cloudfront.net/img/p/11968/c279642.jpg",
							"mobile": "https://d1fl2om3sc0eid.cloudfront.net/img/p/11968/c279642.jpg"
						}
					],
					"days": 13,
					"url": "/mx/circuitos/asia/11968-palacios-y-desiertos-de-rajastan",
					"map": null,
					"highlights": null,
					"includes": null,
					"priceDetail": {
						"fromPrice": 36799,
						"fromPriceBeautify": "$36,799",
						"discountSaved": 0,
						"oldPriceBeautify": "$99",
						"pricingPercentage": 0,
						"pricePerNight": "$3,067"
					},
					"tags": null,
					"crafterDetail": null,
					"hasPrivateTour": false,
					"hasSoloTraveller": true,
					"headLine": null,
					"tagHeadLine": [],
					"isLandOnly": false,
					"isValid": true,
					"extraNights": 0
				},
				{
					"id": 12042,
					"title": "Reino Hachemita, Pirámides & Crucero Nilo",
					"destination": "Jordania y Egipto",
					"images": [
						{
							"desktop": "https://d1fl2om3sc0eid.cloudfront.net/img/p/12042/c259683.jpg",
							"tablet": "https://d1fl2om3sc0eid.cloudfront.net/img/p/12042/c259683.jpg",
							"mobile": "https://d1fl2om3sc0eid.cloudfront.net/img/p/12042/c259683.jpg"
						}
					],
					"days": 16,
					"url": "/mx/circuitos/asia/12042-reino-hachemita-piramides-crucero-nilo",
					"map": null,
					"highlights": null,
					"includes": null,
					"priceDetail": {
						"fromPrice": 60099,
						"fromPriceBeautify": "$60,099",
						"discountSaved": 32460,
						"oldPriceBeautify": "$92,599",
						"pricingPercentage": 35,
						"pricePerNight": "$4,007"
					},
					"tags": null,
					"crafterDetail": null,
					"hasPrivateTour": false,
					"hasSoloTraveller": true,
					"headLine": null,
					"tagHeadLine": [],
					"isLandOnly": false,
					"isValid": true,
					"extraNights": 0
				},
				{
					"id": 11971,
					"title": "Lujo en Dubái y Todo incluido en el edén",
					"destination": "Emiratos Árabes y Maldivas",
					"images": [
						{
							"desktop": "https://d1fl2om3sc0eid.cloudfront.net/img/p/11971/c258443.jpg",
							"tablet": "https://d1fl2om3sc0eid.cloudfront.net/img/p/11971/c258443.jpg",
							"mobile": "https://d1fl2om3sc0eid.cloudfront.net/img/p/11971/c258443.jpg"
						}
					],
					"days": 12,
					"url": "/mx/playas/asia/11971-lujo-en-dubai-y-todo-incluido-en-el-eden",
					"map": null,
					"highlights": null,
					"includes": null,
					"priceDetail": {
						"fromPrice": 66399,
						"fromPriceBeautify": "$66,399",
						"discountSaved": 28560,
						"oldPriceBeautify": "$94,999",
						"pricingPercentage": 30,
						"pricePerNight": "$6,036"
					},
					"tags": null,
					"crafterDetail": null,
					"hasPrivateTour": false,
					"hasSoloTraveller": true,
					"headLine": null,
					"tagHeadLine": [],
					"isLandOnly": false,
					"isValid": true,
					"extraNights": 10
				},
				{
					"id": 12051,
					"title": "Playas, arrozales y junglas",
					"destination": "Indonesia",
					"images": [
						{
							"desktop": "https://d1fl2om3sc0eid.cloudfront.net/img/p/12051/c259850.jpg",
							"tablet": "https://d1fl2om3sc0eid.cloudfront.net/img/p/12051/c259850.jpg",
							"mobile": "https://d1fl2om3sc0eid.cloudfront.net/img/p/12051/c259850.jpg"
						}
					],
					"days": 20,
					"url": "/mx/circuitos/asia/12051-playas-arrozales-y-junglas",
					"map": null,
					"highlights": null,
					"includes": null,
					"priceDetail": {
						"fromPrice": 62399,
						"fromPriceBeautify": "$62,399",
						"discountSaved": 0,
						"oldPriceBeautify": "$99",
						"pricingPercentage": 0,
						"pricePerNight": "$3,284"
					},
					"tags": null,
					"crafterDetail": null,
					"hasPrivateTour": false,
					"hasSoloTraveller": true,
					"headLine": null,
					"tagHeadLine": [],
					"isLandOnly": false,
					"isValid": true,
					"extraNights": 9
				},
				{
					"id": 12099,
					"title": "Reino Hachemita y Encantos de Tierra Santa",
					"destination": "Jordania e Israel",
					"images": [
						{
							"desktop": "https://d1fl2om3sc0eid.cloudfront.net/img/p/12099/c261644.jpg",
							"tablet": "https://d1fl2om3sc0eid.cloudfront.net/img/p/12099/c261644.jpg",
							"mobile": "https://d1fl2om3sc0eid.cloudfront.net/img/p/12099/c261644.jpg"
						}
					],
					"days": 13,
					"url": "/mx/circuitos/asia/12099-reino-hachemita-y-encantos-de-tierra-santa",
					"map": null,
					"highlights": null,
					"includes": null,
					"priceDetail": {
						"fromPrice": 63599,
						"fromPriceBeautify": "$63,599",
						"discountSaved": 38160,
						"oldPriceBeautify": "$101,799",
						"pricingPercentage": 37,
						"pricePerNight": "$5,300"
					},
					"tags": null,
					"crafterDetail": null,
					"hasPrivateTour": false,
					"hasSoloTraveller": true,
					"headLine": null,
					"tagHeadLine": [],
					"isLandOnly": false,
					"isValid": true,
					"extraNights": 0
				},
				{
					"id": 12101,
					"title": "El Enigma de las Pirámides y Tierra Santa",
					"destination": "Egipto e Israel",
					"images": [
						{
							"desktop": "https://d1fl2om3sc0eid.cloudfront.net/img/p/12101/c260756.jpg",
							"tablet": "https://d1fl2om3sc0eid.cloudfront.net/img/p/12101/c260756.jpg",
							"mobile": "https://d1fl2om3sc0eid.cloudfront.net/img/p/12101/c260756.jpg"
						}
					],
					"days": 13,
					"url": "/mx/circuitos/africa/12101-el-enigma-de-las-piramides-y-tierra-santa",
					"map": null,
					"highlights": null,
					"includes": null,
					"priceDetail": {
						"fromPrice": 79399,
						"fromPriceBeautify": "$79,399",
						"discountSaved": 27910,
						"oldPriceBeautify": "$107,399",
						"pricingPercentage": 26,
						"pricePerNight": "$6,617"
					},
					"tags": null,
					"crafterDetail": null,
					"hasPrivateTour": false,
					"hasSoloTraveller": true,
					"headLine": null,
					"tagHeadLine": [],
					"isLandOnly": false,
					"isValid": true,
					"extraNights": 0
				},
				{
					"id": 12040,
					"title": "Triángulo Dorado Turco",
					"destination": "Turquía",
					"images": [
						{
							"desktop": "https://d1fl2om3sc0eid.cloudfront.net/img/p/12040/c259641.jpg",
							"tablet": "https://d1fl2om3sc0eid.cloudfront.net/img/p/12040/c259641.jpg",
							"mobile": "https://d1fl2om3sc0eid.cloudfront.net/img/p/12040/c259641.jpg"
						}
					],
					"days": 8,
					"url": "/mx/circuitos/europa/12040-triangulo-dorado-turco",
					"map": null,
					"highlights": null,
					"includes": null,
					"priceDetail": {
						"fromPrice": 55299,
						"fromPriceBeautify": "$55,299",
						"discountSaved": 0,
						"oldPriceBeautify": "$99",
						"pricingPercentage": 0,
						"pricePerNight": "$7,900"
					},
					"tags": null,
					"crafterDetail": null,
					"hasPrivateTour": false,
					"hasSoloTraveller": true,
					"headLine": null,
					"tagHeadLine": [],
					"isLandOnly": false,
					"isValid": true,
					"extraNights": 0
				}
			]
		},
		{
			"name": "Africa",
			"description": "Adéntrate en las inagotables planicies africanas y disfruta de un safari inolvidable. Deja que la magnífica biodiversidad del continente te sorprenda y descubre la interesante historia de las civilizaciones antiguas y modernas.\n                           ",
			"totalCampaigns": 14,
			"slug": "/mx/africa",
			"type": "continent",
			"title": "Descubre <span>África</span>",
			"icon": "africa-stamp",
			"background": "3_bg",
			"cards": [
				{
					"id": 11575,
					"title": "Grandes Pirámides y crucero por el Nilo",
					"destination": "Egipto",
					"images": [
						{
							"desktop": "https://d1fl2om3sc0eid.cloudfront.net/img/p/11575/c251542.jpg",
							"tablet": "https://d1fl2om3sc0eid.cloudfront.net/img/p/11575/c251542.jpg",
							"mobile": "https://d1fl2om3sc0eid.cloudfront.net/img/p/11575/c251542.jpg"
						}
					],
					"days": 8,
					"url": "/mx/circuitos/africa/11575-grandes-piramides-y-crucero-por-el-nilo",
					"map": null,
					"highlights": null,
					"includes": null,
					"priceDetail": {
						"fromPrice": 38399,
						"fromPriceBeautify": "$38,399",
						"discountSaved": 14600,
						"oldPriceBeautify": "$52,999",
						"pricingPercentage": 27,
						"pricePerNight": "$5,486"
					},
					"tags": null,
					"crafterDetail": null,
					"hasPrivateTour": false,
					"hasSoloTraveller": true,
					"headLine": null,
					"tagHeadLine": [],
					"isLandOnly": false,
					"isValid": true,
					"extraNights": 0
				},
				{
					"id": 11964,
					"title": "Safari en Kruger y Ciudad del Cabo",
					"destination": "Sudáfrica ",
					"images": [
						{
							"desktop": "https://d1fl2om3sc0eid.cloudfront.net/img/p/11964/c258337.jpg",
							"tablet": "https://d1fl2om3sc0eid.cloudfront.net/img/p/11964/c258337.jpg",
							"mobile": "https://d1fl2om3sc0eid.cloudfront.net/img/p/11964/c258337.jpg"
						}
					],
					"days": 9,
					"url": "/mx/naturaleza/africa/11964-safari-en-kruger-y-ciudad-del-cabo",
					"map": null,
					"highlights": null,
					"includes": null,
					"priceDetail": {
						"fromPrice": 50099,
						"fromPriceBeautify": "$50,099",
						"discountSaved": 42090,
						"oldPriceBeautify": "$92,199",
						"pricingPercentage": 45,
						"pricePerNight": "$6,262"
					},
					"tags": null,
					"crafterDetail": null,
					"hasPrivateTour": false,
					"hasSoloTraveller": true,
					"headLine": null,
					"tagHeadLine": [],
					"isLandOnly": false,
					"isValid": true,
					"extraNights": 0
				},
				{
					"id": 11969,
					"title": "Hechizo bereber entre medinas y kasbahs",
					"destination": "Marruecos",
					"images": [
						{
							"desktop": "https://d1fl2om3sc0eid.cloudfront.net/img/p/11969/c258410.jpg",
							"tablet": "https://d1fl2om3sc0eid.cloudfront.net/img/p/11969/c258410.jpg",
							"mobile": "https://d1fl2om3sc0eid.cloudfront.net/img/p/11969/c258410.jpg"
						}
					],
					"days": 10,
					"url": "/mx/circuitos/africa/11969-hechizo-bereber-entre-medinas-y-kasbahs",
					"map": null,
					"highlights": null,
					"includes": null,
					"priceDetail": {
						"fromPrice": 37199,
						"fromPriceBeautify": "$37,199",
						"discountSaved": 27160,
						"oldPriceBeautify": "$64,399",
						"pricingPercentage": 42,
						"pricePerNight": "$4,133"
					},
					"tags": null,
					"crafterDetail": null,
					"hasPrivateTour": false,
					"hasSoloTraveller": true,
					"headLine": null,
					"tagHeadLine": [],
					"isLandOnly": false,
					"isValid": true,
					"extraNights": 0
				},
				{
					"id": 12050,
					"title": "Pirámides, Nilo y Hurgada Todo Incl.",
					"destination": "Egipto",
					"images": [
						{
							"desktop": "https://d1fl2om3sc0eid.cloudfront.net/img/p/12050/c259823.jpg",
							"tablet": "https://d1fl2om3sc0eid.cloudfront.net/img/p/12050/c259823.jpg",
							"mobile": "https://d1fl2om3sc0eid.cloudfront.net/img/p/12050/c259823.jpg"
						}
					],
					"days": 12,
					"url": "/mx/circuitos/africa/12050-piramides-nilo-y-hurgada-todo-incl",
					"map": null,
					"highlights": null,
					"includes": null,
					"priceDetail": {
						"fromPrice": 56799,
						"fromPriceBeautify": "$56,799",
						"discountSaved": 11640,
						"oldPriceBeautify": "$68,499",
						"pricingPercentage": 16,
						"pricePerNight": "$5,164"
					},
					"tags": null,
					"crafterDetail": null,
					"hasPrivateTour": false,
					"hasSoloTraveller": true,
					"headLine": null,
					"tagHeadLine": [],
					"isLandOnly": false,
					"isValid": true,
					"extraNights": 0
				},
				{
					"id": 12042,
					"title": "Reino Hachemita, Pirámides & Crucero Nilo",
					"destination": "Jordania y Egipto",
					"images": [
						{
							"desktop": "https://d1fl2om3sc0eid.cloudfront.net/img/p/12042/c259683.jpg",
							"tablet": "https://d1fl2om3sc0eid.cloudfront.net/img/p/12042/c259683.jpg",
							"mobile": "https://d1fl2om3sc0eid.cloudfront.net/img/p/12042/c259683.jpg"
						}
					],
					"days": 16,
					"url": "/mx/circuitos/asia/12042-reino-hachemita-piramides-crucero-nilo",
					"map": null,
					"highlights": null,
					"includes": null,
					"priceDetail": {
						"fromPrice": 60099,
						"fromPriceBeautify": "$60,099",
						"discountSaved": 32460,
						"oldPriceBeautify": "$92,599",
						"pricingPercentage": 35,
						"pricePerNight": "$4,007"
					},
					"tags": null,
					"crafterDetail": null,
					"hasPrivateTour": false,
					"hasSoloTraveller": true,
					"headLine": null,
					"tagHeadLine": [],
					"isLandOnly": false,
					"isValid": true,
					"extraNights": 0
				},
				{
					"id": 12048,
					"title": "Aventura africana de lujo",
					"destination": "Kenia  ",
					"images": [
						{
							"desktop": "https://d1fl2om3sc0eid.cloudfront.net/img/p/12048/c259796.jpg",
							"tablet": "https://d1fl2om3sc0eid.cloudfront.net/img/p/12048/c259796.jpg",
							"mobile": "https://d1fl2om3sc0eid.cloudfront.net/img/p/12048/c259796.jpg"
						}
					],
					"days": 11,
					"url": "/mx/naturaleza/africa/12048-aventura-africana-de-lujo",
					"map": null,
					"highlights": null,
					"includes": null,
					"priceDetail": {
						"fromPrice": 66199,
						"fromPriceBeautify": "$66,199",
						"discountSaved": 43030,
						"oldPriceBeautify": "$109,299",
						"pricingPercentage": 39,
						"pricePerNight": "$6,620"
					},
					"tags": null,
					"crafterDetail": null,
					"hasPrivateTour": false,
					"hasSoloTraveller": true,
					"headLine": null,
					"tagHeadLine": [],
					"isLandOnly": false,
					"isValid": true,
					"extraNights": 0
				},
				{
					"id": 12070,
					"title": "El Paraíso Terrenal Todo incluido",
					"destination": "Mauricio",
					"images": [
						{
							"desktop": "https://d1fl2om3sc0eid.cloudfront.net/img/p/12070/c260186.jpg",
							"tablet": "https://d1fl2om3sc0eid.cloudfront.net/img/p/12070/c260186.jpg",
							"mobile": "https://d1fl2om3sc0eid.cloudfront.net/img/p/12070/c260186.jpg"
						}
					],
					"days": 9,
					"url": "/mx/naturaleza/africa/12070-el-paraiso-terrenal-todo-incluido",
					"map": null,
					"highlights": null,
					"includes": null,
					"priceDetail": {
						"fromPrice": 70499,
						"fromPriceBeautify": "$70,499",
						"discountSaved": 69090,
						"oldPriceBeautify": "$139,599",
						"pricingPercentage": 49,
						"pricePerNight": "$8,812"
					},
					"tags": null,
					"crafterDetail": null,
					"hasPrivateTour": false,
					"hasSoloTraveller": true,
					"headLine": null,
					"tagHeadLine": [],
					"isLandOnly": false,
					"isValid": true,
					"extraNights": 9
				},
				{
					"id": 12055,
					"title": "Sabana Salvaje y Escapada de Relax",
					"destination": "Kenia",
					"images": [
						{
							"desktop": "https://d1fl2om3sc0eid.cloudfront.net/img/p/12055/c259924.jpg",
							"tablet": "https://d1fl2om3sc0eid.cloudfront.net/img/p/12055/c259924.jpg",
							"mobile": "https://d1fl2om3sc0eid.cloudfront.net/img/p/12055/c259924.jpg"
						}
					],
					"days": 12,
					"url": "/mx/circuitos/africa/12055-sabana-salvaje-y-escapada-de-relax",
					"map": null,
					"highlights": null,
					"includes": null,
					"priceDetail": {
						"fromPrice": 68899,
						"fromPriceBeautify": "$68,899",
						"discountSaved": 31010,
						"oldPriceBeautify": "$99,999",
						"pricingPercentage": 31,
						"pricePerNight": "$6,264"
					},
					"tags": null,
					"crafterDetail": null,
					"hasPrivateTour": false,
					"hasSoloTraveller": true,
					"headLine": null,
					"tagHeadLine": [],
					"isLandOnly": false,
					"isValid": true,
					"extraNights": 0
				},
				{
					"id": 12045,
					"title": "Capitales imperiales y las mil Kasbah",
					"destination": "Marruecos",
					"images": [
						{
							"desktop": "https://d1fl2om3sc0eid.cloudfront.net/img/p/12045/c259739.jpg",
							"tablet": "https://d1fl2om3sc0eid.cloudfront.net/img/p/12045/c259739.jpg",
							"mobile": "https://d1fl2om3sc0eid.cloudfront.net/img/p/12045/c259739.jpg"
						}
					],
					"days": 9,
					"url": "/mx/circuitos/africa/12045-capitales-imperiales-y-las-mil-kasbah",
					"map": null,
					"highlights": null,
					"includes": null,
					"priceDetail": {
						"fromPrice": 32999,
						"fromPriceBeautify": "$32,999",
						"discountSaved": 30360,
						"oldPriceBeautify": "$63,399",
						"pricingPercentage": 47,
						"pricePerNight": "$4,125"
					},
					"tags": null,
					"crafterDetail": null,
					"hasPrivateTour": false,
					"hasSoloTraveller": true,
					"headLine": null,
					"tagHeadLine": [],
					"isLandOnly": false,
					"isValid": true,
					"extraNights": 0
				},
				{
					"id": 11965,
					"title": "Ciudades, safaris y cataratas",
					"destination": "Sudáfrica y Zimbabue",
					"images": [
						{
							"desktop": "https://d1fl2om3sc0eid.cloudfront.net/img/p/11965/c258350.jpg",
							"tablet": "https://d1fl2om3sc0eid.cloudfront.net/img/p/11965/c258350.jpg",
							"mobile": "https://d1fl2om3sc0eid.cloudfront.net/img/p/11965/c258350.jpg"
						}
					],
					"days": 13,
					"url": "/mx/naturaleza/africa/11965-ciudades-safaris-y-cataratas",
					"map": null,
					"highlights": null,
					"includes": null,
					"priceDetail": {
						"fromPrice": 82899,
						"fromPriceBeautify": "$82,899",
						"discountSaved": 63840,
						"oldPriceBeautify": "$146,799",
						"pricingPercentage": 43,
						"pricePerNight": "$6,908"
					},
					"tags": null,
					"crafterDetail": null,
					"hasPrivateTour": false,
					"hasSoloTraveller": true,
					"headLine": null,
					"tagHeadLine": [],
					"isLandOnly": false,
					"isValid": true,
					"extraNights": 0
				}
			]
		},
		{
			"name": "Europa",
			"description": "Vive en primera persona la armoniosa fusión entre lo clásico y lo moderno. Descubre la esencia única de cada país y maravíllate con su diversidad.\n                            ",
			"totalCampaigns": 14,
			"slug": "/mx/europa",
			"type": "continent",
			"title": "Saborea <span>Europa</span>",
			"icon": "europa-stamp",
			"background": "4_bg",
			"cards": [
				{
					"id": 12058,
					"title": "Ciudad Eterna, Catedrales y Góndolas",
					"destination": "Italia",
					"images": [
						{
							"desktop": "https://d1fl2om3sc0eid.cloudfront.net/img/p/12058/c259971.jpg",
							"tablet": "https://d1fl2om3sc0eid.cloudfront.net/img/p/12058/c259971.jpg",
							"mobile": "https://d1fl2om3sc0eid.cloudfront.net/img/p/12058/c259971.jpg"
						}
					],
					"days": 10,
					"url": "/mx/circuitos/europa/12058-ciudad-eterna-catedrales-y-gondolas",
					"map": null,
					"highlights": null,
					"includes": null,
					"priceDetail": {
						"fromPrice": 33099,
						"fromPriceBeautify": "$33,099",
						"discountSaved": 31780,
						"oldPriceBeautify": "$64,899",
						"pricingPercentage": 48,
						"pricePerNight": "$3,678"
					},
					"tags": null,
					"crafterDetail": null,
					"hasPrivateTour": false,
					"hasSoloTraveller": true,
					"headLine": null,
					"tagHeadLine": [],
					"isLandOnly": false,
					"isValid": true,
					"extraNights": 0
				},
				{
					"id": 11559,
					"title": "Capitales de Europa Central",
					"destination": "Alemania, República Checa, Austria y Hungría",
					"images": [
						{
							"desktop": "https://d1fl2om3sc0eid.cloudfront.net/img/p/11559/c251228.jpg",
							"tablet": "https://d1fl2om3sc0eid.cloudfront.net/img/p/11559/c251228.jpg",
							"mobile": "https://d1fl2om3sc0eid.cloudfront.net/img/p/11559/c251228.jpg"
						}
					],
					"days": 12,
					"url": "/mx/circuitos/europa/11559-capitales-de-europa-central",
					"map": null,
					"highlights": null,
					"includes": null,
					"priceDetail": {
						"fromPrice": 55899,
						"fromPriceBeautify": "$55,899",
						"discountSaved": 32840,
						"oldPriceBeautify": "$88,799",
						"pricingPercentage": 37,
						"pricePerNight": "$5,082"
					},
					"tags": null,
					"crafterDetail": null,
					"hasPrivateTour": false,
					"hasSoloTraveller": true,
					"headLine": null,
					"tagHeadLine": [],
					"isLandOnly": false,
					"isValid": true,
					"extraNights": 0
				},
				{
					"id": 12041,
					"title": "Ciudades Costeras y Tesoros Culturales",
					"destination": "Portugal",
					"images": [
						{
							"desktop": "https://d1fl2om3sc0eid.cloudfront.net/img/p/12041/c259660.jpg",
							"tablet": "https://d1fl2om3sc0eid.cloudfront.net/img/p/12041/c259660.jpg",
							"mobile": "https://d1fl2om3sc0eid.cloudfront.net/img/p/12041/c259660.jpg"
						}
					],
					"days": 9,
					"url": "/mx/circuitos/europa/12041-ciudades-costeras-y-tesoros-culturales",
					"map": null,
					"highlights": null,
					"includes": null,
					"priceDetail": {
						"fromPrice": 47499,
						"fromPriceBeautify": "$47,499",
						"discountSaved": 45600,
						"oldPriceBeautify": "$93,099",
						"pricingPercentage": 48,
						"pricePerNight": "$5,937"
					},
					"tags": null,
					"crafterDetail": null,
					"hasPrivateTour": false,
					"hasSoloTraveller": true,
					"headLine": null,
					"tagHeadLine": [],
					"isLandOnly": false,
					"isValid": true,
					"extraNights": 3
				},
				{
					"id": 12700,
					"title": "Alpes, puentes y góndolas",
					"destination": "Suiza e Italia",
					"images": [
						{
							"desktop": "https://d1fl2om3sc0eid.cloudfront.net/img/p/12700/c271679.jpg",
							"tablet": "https://d1fl2om3sc0eid.cloudfront.net/img/p/12700/c271679.jpg",
							"mobile": "https://d1fl2om3sc0eid.cloudfront.net/img/p/12700/c271679.jpg"
						}
					],
					"days": 16,
					"url": "/mx/circuitos/europa/12700-alpes-puentes-y-gondolas",
					"map": null,
					"highlights": null,
					"includes": null,
					"priceDetail": {
						"fromPrice": 80799,
						"fromPriceBeautify": "$80,799",
						"discountSaved": 79190,
						"oldPriceBeautify": "$159,999",
						"pricingPercentage": 49,
						"pricePerNight": "$5,387"
					},
					"tags": null,
					"crafterDetail": null,
					"hasPrivateTour": false,
					"hasSoloTraveller": false,
					"headLine": null,
					"tagHeadLine": [],
					"isLandOnly": false,
					"isValid": true,
					"extraNights": 0
				},
				{
					"id": 12912,
					"title": "Castillos y Maravillas Celtas",
					"destination": "Irlanda, Escocia e Inglaterra",
					"images": [
						{
							"desktop": "https://d1fl2om3sc0eid.cloudfront.net/img/p/12912/c275567.jpg",
							"tablet": "https://d1fl2om3sc0eid.cloudfront.net/img/p/12912/c275567.jpg",
							"mobile": "https://d1fl2om3sc0eid.cloudfront.net/img/p/12912/c275567.jpg"
						}
					],
					"days": 14,
					"url": "/mx/circuitos/europa/12912-castillos-y-maravillas-celtas",
					"map": null,
					"highlights": null,
					"includes": null,
					"priceDetail": {
						"fromPrice": 67199,
						"fromPriceBeautify": "$67,199",
						"discountSaved": 51080,
						"oldPriceBeautify": "$118,299",
						"pricingPercentage": 43,
						"pricePerNight": "$5,169"
					},
					"tags": null,
					"crafterDetail": null,
					"hasPrivateTour": false,
					"hasSoloTraveller": true,
					"headLine": null,
					"tagHeadLine": [],
					"isLandOnly": false,
					"isValid": true,
					"extraNights": 0
				},
				{
					"id": 12937,
					"title": "Ciudades Eternas, Madrid y Barcelona",
					"destination": "Italia y España",
					"images": [
						{
							"desktop": "https://d1fl2om3sc0eid.cloudfront.net/img/p/12937/c286336.jpg",
							"tablet": "https://d1fl2om3sc0eid.cloudfront.net/img/p/12937/c286336.jpg",
							"mobile": "https://d1fl2om3sc0eid.cloudfront.net/img/p/12937/c286336.jpg"
						}
					],
					"days": 16,
					"url": "/mx/circuitos/europa/12937-ciudades-eternas-madrid-y-barcelona",
					"map": null,
					"highlights": null,
					"includes": null,
					"priceDetail": {
						"fromPrice": 52999,
						"fromPriceBeautify": "$52,999",
						"discountSaved": 40280,
						"oldPriceBeautify": "$93,299",
						"pricingPercentage": 43,
						"pricePerNight": "$3,533"
					},
					"tags": null,
					"crafterDetail": null,
					"hasPrivateTour": false,
					"hasSoloTraveller": true,
					"headLine": null,
					"tagHeadLine": [],
					"isLandOnly": false,
					"isValid": true,
					"extraNights": 3
				},
				{
					"id": 12936,
					"title": "Tesoros de Iberia",
					"destination": "Portugal y España",
					"images": [
						{
							"desktop": "https://d1fl2om3sc0eid.cloudfront.net/img/p/12936/c275965.jpg",
							"tablet": "https://d1fl2om3sc0eid.cloudfront.net/img/p/12936/c275965.jpg",
							"mobile": "https://d1fl2om3sc0eid.cloudfront.net/img/p/12936/c275965.jpg"
						}
					],
					"days": 15,
					"url": "/mx/circuitos/europa/12936-tesoros-de-iberia",
					"map": null,
					"highlights": null,
					"includes": null,
					"priceDetail": {
						"fromPrice": 68899,
						"fromPriceBeautify": "$68,899",
						"discountSaved": 68900,
						"oldPriceBeautify": "$137,799",
						"pricingPercentage": 50,
						"pricePerNight": "$4,921"
					},
					"tags": null,
					"crafterDetail": null,
					"hasPrivateTour": false,
					"hasSoloTraveller": false,
					"headLine": null,
					"tagHeadLine": [],
					"isLandOnly": false,
					"isValid": true,
					"extraNights": 3
				},
				{
					"id": 12934,
					"title": "Ciudades Eternas y Tesoros de Iberia",
					"destination": "Italia, Portugal y España",
					"images": [
						{
							"desktop": "https://d1fl2om3sc0eid.cloudfront.net/img/p/12934/c275941.jpg",
							"tablet": "https://d1fl2om3sc0eid.cloudfront.net/img/p/12934/c275941.jpg",
							"mobile": "https://d1fl2om3sc0eid.cloudfront.net/img/p/12934/c275941.jpg"
						}
					],
					"days": 23,
					"url": "/mx/circuitos/europa/12934-ciudades-eternas-y-tesoros-de-iberia",
					"map": null,
					"highlights": null,
					"includes": null,
					"priceDetail": {
						"fromPrice": 81599,
						"fromPriceBeautify": "$81,599",
						"discountSaved": 62020,
						"oldPriceBeautify": "$143,699",
						"pricingPercentage": 43,
						"pricePerNight": "$3,709"
					},
					"tags": null,
					"crafterDetail": null,
					"hasPrivateTour": false,
					"hasSoloTraveller": false,
					"headLine": null,
					"tagHeadLine": [],
					"isLandOnly": false,
					"isValid": true,
					"extraNights": 3
				},
				{
					"id": 13371,
					"title": "Ruinas Asombrosas, Estambul y Capadocia",
					"destination": "Grecia y Turquía ",
					"images": [
						{
							"desktop": "https://d1fl2om3sc0eid.cloudfront.net/img/p/13371/c284350.jpg",
							"tablet": "https://d1fl2om3sc0eid.cloudfront.net/img/p/13371/c284350.jpg",
							"mobile": "https://d1fl2om3sc0eid.cloudfront.net/img/p/13371/c284350.jpg"
						}
					],
					"days": 12,
					"url": "/mx/circuitos/europa/13371-ruinas-asombrosas-estambul-y-capadocia",
					"map": null,
					"highlights": null,
					"includes": null,
					"priceDetail": {
						"fromPrice": 48199,
						"fromPriceBeautify": "$48,199",
						"discountSaved": 48200,
						"oldPriceBeautify": "$96,399",
						"pricingPercentage": 50,
						"pricePerNight": "$4,382"
					},
					"tags": null,
					"crafterDetail": null,
					"hasPrivateTour": false,
					"hasSoloTraveller": false,
					"headLine": null,
					"tagHeadLine": [],
					"isLandOnly": false,
					"isValid": true,
					"extraNights": 0
				},
				{
					"id": 13424,
					"title": "Atenas y Paraísos del Egeo",
					"destination": "Grecia",
					"images": [
						{
							"desktop": "https://d1fl2om3sc0eid.cloudfront.net/img/p/13424/c285414.jpg",
							"tablet": "https://d1fl2om3sc0eid.cloudfront.net/img/p/13424/c285414.jpg",
							"mobile": "https://d1fl2om3sc0eid.cloudfront.net/img/p/13424/c285414.jpg"
						}
					],
					"days": 10,
					"url": "/mx/circuitos/europa/13424-atenas-y-paraisos-del-egeo",
					"map": null,
					"highlights": null,
					"includes": null,
					"priceDetail": {
						"fromPrice": 41299,
						"fromPriceBeautify": "$41,299",
						"discountSaved": 41300,
						"oldPriceBeautify": "$82,599",
						"pricingPercentage": 50,
						"pricePerNight": "$4,589"
					},
					"tags": null,
					"crafterDetail": null,
					"hasPrivateTour": false,
					"hasSoloTraveller": true,
					"headLine": null,
					"tagHeadLine": [],
					"isLandOnly": false,
					"isValid": true,
					"extraNights": 5
				}
			]
		},
		{
			"name": "Oceania",
			"description": "Atrévete a conocer países lejanos. Allí encontrarás playas impolutas, montañas únicas, bosques prehistóricos y algunas de las ciudades más vivas del mundo.\n                            ",
			"totalCampaigns": 1,
			"slug": "/mx/oceania",
			"type": "continent",
			"title": "Explora <span>Oceanía</span>",
			"icon": "oceania-stamp",
			"background": "5_bg",
			"cards": [
				{
					"id": 13452,
					"title": "Aventuras en las profundidades",
					"destination": "Australia",
					"images": [
						{
							"desktop": "https://d1fl2om3sc0eid.cloudfront.net/img/p/13452/c285939.jpg",
							"tablet": "https://d1fl2om3sc0eid.cloudfront.net/img/p/13452/c285939.jpg",
							"mobile": "https://d1fl2om3sc0eid.cloudfront.net/img/p/13452/c285939.jpg"
						}
					],
					"days": 16,
					"url": "/mx/circuitos/oceania/13452-aventuras-en-las-profundidades",
					"map": null,
					"highlights": null,
					"includes": null,
					"priceDetail": {
						"fromPrice": 85199,
						"fromPriceBeautify": "$85,199",
						"discountSaved": 36520,
						"oldPriceBeautify": "$121,799",
						"pricingPercentage": 30,
						"pricePerNight": "$5,680"
					},
					"tags": null,
					"crafterDetail": null,
					"hasPrivateTour": false,
					"hasSoloTraveller": true,
					"headLine": null,
					"tagHeadLine": [],
					"isLandOnly": false,
					"isValid": true,
					"extraNights": 0
				}
			]
		}
	],
	"topSales": {
		"type": "top_sales",
		"title": "Top <span>Selling</span>",
		"icon": "top-selling",
		"background": "Top <span>Selling</span>",
		"cards": [
			{
				"id": 13413,
				"title": "Tesoros de Anatolia y Odisea Griega",
				"destination": "Turquía y Grecia",
				"images": [
					{
						"desktop": "https://d1fl2om3sc0eid.cloudfront.net/img/p/13413/c285203.jpg",
						"tablet": "https://d1fl2om3sc0eid.cloudfront.net/img/p/13413/c285203.jpg",
						"mobile": "https://d1fl2om3sc0eid.cloudfront.net/img/p/13413/c285203.jpg"
					}
				],
				"days": 17,
				"url": "/mx/circuitos/europa/13413-tesoros-de-anatolia-y-odisea-griega",
				"map": null,
				"highlights": null,
				"includes": null,
				"priceDetail": {
					"fromPrice": 67099,
					"fromPriceBeautify": "$67,099",
					"discountSaved": 67100,
					"oldPriceBeautify": "$134,199",
					"pricingPercentage": 50,
					"pricePerNight": "$4,194"
				},
				"tags": null,
				"crafterDetail": null,
				"hasPrivateTour": false,
				"hasSoloTraveller": false,
				"headLine": null,
				"tagHeadLine": [],
				"isLandOnly": false,
				"isValid": true,
				"extraNights": 5
			},
			{
				"id": 12937,
				"title": "Ciudades Eternas, Madrid y Barcelona",
				"destination": "Italia y España",
				"images": [
					{
						"desktop": "https://d1fl2om3sc0eid.cloudfront.net/img/p/12937/c286336.jpg",
						"tablet": "https://d1fl2om3sc0eid.cloudfront.net/img/p/12937/c286336.jpg",
						"mobile": "https://d1fl2om3sc0eid.cloudfront.net/img/p/12937/c286336.jpg"
					}
				],
				"days": 16,
				"url": "/mx/circuitos/europa/12937-ciudades-eternas-madrid-y-barcelona",
				"map": null,
				"highlights": null,
				"includes": null,
				"priceDetail": {
					"fromPrice": 52999,
					"fromPriceBeautify": "$52,999",
					"discountSaved": 40280,
					"oldPriceBeautify": "$93,299",
					"pricingPercentage": 43,
					"pricePerNight": "$3,533"
				},
				"tags": null,
				"crafterDetail": null,
				"hasPrivateTour": false,
				"hasSoloTraveller": true,
				"headLine": null,
				"tagHeadLine": [],
				"isLandOnly": false,
				"isValid": true,
				"extraNights": 3
			},
			{
				"id": 12042,
				"title": "Reino Hachemita, Pirámides & Crucero Nilo",
				"destination": "Jordania y Egipto",
				"images": [
					{
						"desktop": "https://d1fl2om3sc0eid.cloudfront.net/img/p/12042/c259683.jpg",
						"tablet": "https://d1fl2om3sc0eid.cloudfront.net/img/p/12042/c259683.jpg",
						"mobile": "https://d1fl2om3sc0eid.cloudfront.net/img/p/12042/c259683.jpg"
					}
				],
				"days": 16,
				"url": "/mx/circuitos/asia/12042-reino-hachemita-piramides-crucero-nilo",
				"map": null,
				"highlights": null,
				"includes": null,
				"priceDetail": {
					"fromPrice": 60099,
					"fromPriceBeautify": "$60,099",
					"discountSaved": 32460,
					"oldPriceBeautify": "$92,599",
					"pricingPercentage": 35,
					"pricePerNight": "$4,007"
				},
				"tags": null,
				"crafterDetail": null,
				"hasPrivateTour": false,
				"hasSoloTraveller": true,
				"headLine": null,
				"tagHeadLine": [],
				"isLandOnly": false,
				"isValid": true,
				"extraNights": 0
			},
			{
				"id": 11559,
				"title": "Capitales de Europa Central",
				"destination": "Alemania, República Checa, Austria y Hungría",
				"images": [
					{
						"desktop": "https://d1fl2om3sc0eid.cloudfront.net/img/p/11559/c251228.jpg",
						"tablet": "https://d1fl2om3sc0eid.cloudfront.net/img/p/11559/c251228.jpg",
						"mobile": "https://d1fl2om3sc0eid.cloudfront.net/img/p/11559/c251228.jpg"
					}
				],
				"days": 12,
				"url": "/mx/circuitos/europa/11559-capitales-de-europa-central",
				"map": null,
				"highlights": null,
				"includes": null,
				"priceDetail": {
					"fromPrice": 55899,
					"fromPriceBeautify": "$55,899",
					"discountSaved": 32840,
					"oldPriceBeautify": "$88,799",
					"pricingPercentage": 37,
					"pricePerNight": "$5,082"
				},
				"tags": null,
				"crafterDetail": null,
				"hasPrivateTour": false,
				"hasSoloTraveller": true,
				"headLine": null,
				"tagHeadLine": [],
				"isLandOnly": false,
				"isValid": true,
				"extraNights": 0
			},
			{
				"id": 11573,
				"title": "Pura Vida y Paraíso en Tamarindo",
				"destination": "Costa Rica",
				"images": [
					{
						"desktop": "https://d1fl2om3sc0eid.cloudfront.net/img/p/11573/c251511.jpg",
						"tablet": "https://d1fl2om3sc0eid.cloudfront.net/img/p/11573/c251511.jpg",
						"mobile": "https://d1fl2om3sc0eid.cloudfront.net/img/p/11573/c251511.jpg"
					}
				],
				"days": 10,
				"url": "/mx/naturaleza/america/11573-pura-vida-y-paraiso-en-tamarindo",
				"map": null,
				"highlights": null,
				"includes": null,
				"priceDetail": {
					"fromPrice": 25199,
					"fromPriceBeautify": "$25,199",
					"discountSaved": 11090,
					"oldPriceBeautify": "$36,299",
					"pricingPercentage": 30,
					"pricePerNight": "$2,800"
				},
				"tags": null,
				"crafterDetail": null,
				"hasPrivateTour": false,
				"hasSoloTraveller": true,
				"headLine": null,
				"tagHeadLine": [],
				"isLandOnly": false,
				"isValid": true,
				"extraNights": 0
			},
			{
				"id": 11969,
				"title": "Hechizo bereber entre medinas y kasbahs",
				"destination": "Marruecos",
				"images": [
					{
						"desktop": "https://d1fl2om3sc0eid.cloudfront.net/img/p/11969/c258410.jpg",
						"tablet": "https://d1fl2om3sc0eid.cloudfront.net/img/p/11969/c258410.jpg",
						"mobile": "https://d1fl2om3sc0eid.cloudfront.net/img/p/11969/c258410.jpg"
					}
				],
				"days": 10,
				"url": "/mx/circuitos/africa/11969-hechizo-bereber-entre-medinas-y-kasbahs",
				"map": null,
				"highlights": null,
				"includes": null,
				"priceDetail": {
					"fromPrice": 37199,
					"fromPriceBeautify": "$37,199",
					"discountSaved": 27160,
					"oldPriceBeautify": "$64,399",
					"pricingPercentage": 42,
					"pricePerNight": "$4,133"
				},
				"tags": null,
				"crafterDetail": null,
				"hasPrivateTour": false,
				"hasSoloTraveller": true,
				"headLine": null,
				"tagHeadLine": [],
				"isLandOnly": false,
				"isValid": true,
				"extraNights": 0
			},
			{
				"id": 13452,
				"title": "Aventuras en las profundidades",
				"destination": "Australia",
				"images": [
					{
						"desktop": "https://d1fl2om3sc0eid.cloudfront.net/img/p/13452/c285939.jpg",
						"tablet": "https://d1fl2om3sc0eid.cloudfront.net/img/p/13452/c285939.jpg",
						"mobile": "https://d1fl2om3sc0eid.cloudfront.net/img/p/13452/c285939.jpg"
					}
				],
				"days": 16,
				"url": "/mx/circuitos/oceania/13452-aventuras-en-las-profundidades",
				"map": null,
				"highlights": null,
				"includes": null,
				"priceDetail": {
					"fromPrice": 85199,
					"fromPriceBeautify": "$85,199",
					"discountSaved": 36520,
					"oldPriceBeautify": "$121,799",
					"pricingPercentage": 30,
					"pricePerNight": "$5,680"
				},
				"tags": null,
				"crafterDetail": null,
				"hasPrivateTour": false,
				"hasSoloTraveller": true,
				"headLine": null,
				"tagHeadLine": [],
				"isLandOnly": false,
				"isValid": true,
				"extraNights": 0
			},
			{
				"id": 12912,
				"title": "Castillos y Maravillas Celtas",
				"destination": "Irlanda, Escocia e Inglaterra",
				"images": [
					{
						"desktop": "https://d1fl2om3sc0eid.cloudfront.net/img/p/12912/c275567.jpg",
						"tablet": "https://d1fl2om3sc0eid.cloudfront.net/img/p/12912/c275567.jpg",
						"mobile": "https://d1fl2om3sc0eid.cloudfront.net/img/p/12912/c275567.jpg"
					}
				],
				"days": 14,
				"url": "/mx/circuitos/europa/12912-castillos-y-maravillas-celtas",
				"map": null,
				"highlights": null,
				"includes": null,
				"priceDetail": {
					"fromPrice": 67199,
					"fromPriceBeautify": "$67,199",
					"discountSaved": 51080,
					"oldPriceBeautify": "$118,299",
					"pricingPercentage": 43,
					"pricePerNight": "$5,169"
				},
				"tags": null,
				"crafterDetail": null,
				"hasPrivateTour": false,
				"hasSoloTraveller": true,
				"headLine": null,
				"tagHeadLine": [],
				"isLandOnly": false,
				"isValid": true,
				"extraNights": 0
			},
			{
				"id": 11967,
				"title": "Bangkok, Angkor y Bahía de Halong",
				"destination": "Tailandia, Camboya y Vietnam",
				"images": [
					{
						"desktop": "https://d1fl2om3sc0eid.cloudfront.net/img/p/11967/c258383.jpg",
						"tablet": "https://d1fl2om3sc0eid.cloudfront.net/img/p/11967/c258383.jpg",
						"mobile": "https://d1fl2om3sc0eid.cloudfront.net/img/p/11967/c258383.jpg"
					}
				],
				"days": 19,
				"url": "/mx/circuitos/asia/11967-bangkok-angkor-y-bahia-de-halong",
				"map": null,
				"highlights": null,
				"includes": null,
				"priceDetail": {
					"fromPrice": 61999,
					"fromPriceBeautify": "$61,999",
					"discountSaved": 39060,
					"oldPriceBeautify": "$101,099",
					"pricingPercentage": 38,
					"pricePerNight": "$3,444"
				},
				"tags": null,
				"crafterDetail": null,
				"hasPrivateTour": false,
				"hasSoloTraveller": true,
				"headLine": null,
				"tagHeadLine": [],
				"isLandOnly": false,
				"isValid": true,
				"extraNights": 0
			},
			{
				"id": 12048,
				"title": "Aventura africana de lujo",
				"destination": "Kenia  ",
				"images": [
					{
						"desktop": "https://d1fl2om3sc0eid.cloudfront.net/img/p/12048/c259796.jpg",
						"tablet": "https://d1fl2om3sc0eid.cloudfront.net/img/p/12048/c259796.jpg",
						"mobile": "https://d1fl2om3sc0eid.cloudfront.net/img/p/12048/c259796.jpg"
					}
				],
				"days": 11,
				"url": "/mx/naturaleza/africa/12048-aventura-africana-de-lujo",
				"map": null,
				"highlights": null,
				"includes": null,
				"priceDetail": {
					"fromPrice": 66199,
					"fromPriceBeautify": "$66,199",
					"discountSaved": 43030,
					"oldPriceBeautify": "$109,299",
					"pricingPercentage": 39,
					"pricePerNight": "$6,620"
				},
				"tags": null,
				"crafterDetail": null,
				"hasPrivateTour": false,
				"hasSoloTraveller": true,
				"headLine": null,
				"tagHeadLine": [],
				"isLandOnly": false,
				"isValid": true,
				"extraNights": 0
			}
		]
	}
}
